{
  "PackageData": [
    {
      "Row": [
        {
          "SchemaColumnUId": "ae0e45ca-c495-4fe7-a39d-3ab7278e1617",
          "ColumnName": "Id",
          "Value": "393be1ba-016e-4e26-a624-a9b54d84cb3f"
        },
        {
          "SchemaColumnUId": "736c30a7-c0ec-4fa9-b034-2552b319b633",
          "ColumnName": "Name",
          "Value": ""
        },
        {
          "SchemaColumnUId": "9e53fd7c-dde4-4502-a64c-b9e34148108b",
          "ColumnName": "Description",
          "Value": ""
        }
      ]
    },
    {
      "Row": [
        {
          "SchemaColumnUId": "ae0e45ca-c495-4fe7-a39d-3ab7278e1617",
          "ColumnName": "Id",
          "Value": "818b8f71-7637-4cfa-a2ca-f2bacbeb4d27"
        },
        {
          "SchemaColumnUId": "736c30a7-c0ec-4fa9-b034-2552b319b633",
          "ColumnName": "Name",
          "Value": ""
        },
        {
          "SchemaColumnUId": "9e53fd7c-dde4-4502-a64c-b9e34148108b",
          "ColumnName": "Description",
          "Value": ""
        }
      ]
    },
    {
      "Row": [
        {
          "SchemaColumnUId": "ae0e45ca-c495-4fe7-a39d-3ab7278e1617",
          "ColumnName": "Id",
          "Value": "ed43f0f6-3d97-4221-a085-707de667773f"
        },
        {
          "SchemaColumnUId": "736c30a7-c0ec-4fa9-b034-2552b319b633",
          "ColumnName": "Name",
          "Value": ""
        },
        {
          "SchemaColumnUId": "9e53fd7c-dde4-4502-a64c-b9e34148108b",
          "ColumnName": "Description",
          "Value": ""
        }
      ]
    },
    {
      "Row": [
        {
          "SchemaColumnUId": "ae0e45ca-c495-4fe7-a39d-3ab7278e1617",
          "ColumnName": "Id",
          "Value": "f9f79760-f393-459b-b2fd-3986705e54e5"
        },
        {
          "SchemaColumnUId": "736c30a7-c0ec-4fa9-b034-2552b319b633",
          "ColumnName": "Name",
          "Value": ""
        },
        {
          "SchemaColumnUId": "9e53fd7c-dde4-4502-a64c-b9e34148108b",
          "ColumnName": "Description",
          "Value": ""
        }
      ]
    }
  ]
}